dictionary_english/__init__.py
dictionary_english/english.py
dictionary_english/data/www.txt
dictionary_english-0.3.0.dist-info/licenses/LICENSE
dictionary_english-0.3.0.dist-info/METADATA
dictionary_english-0.3.0.dist-info/WHEEL
dictionary_english-0.3.0.dist-info/top_level.txt
dictionary_english-0.3.0.dist-info/RECORD
