Metadata-Version: 2.4
Name: dictionary-english
Version: 0.3.0
Summary: A simple English dictionary API client for Python
Author-email: WooYoung Moon <wymoon2690@gmail.com>
License:                     GNU GENERAL PUBLIC LICENSE
Project-URL: Github, https://github.com/bluetsys/dictionary-english
Project-URL: Bug Tracker, https://github.com/bluetsys/dictionary-english/issues
Requires-Python: >=3.9
License-File: LICENSE
Requires-Dist: requests>=2.32.3
Dynamic: license-file
